{
  "version": 2.0,
  "questions": [
    {
      "question": "How many transition functions does a NFA have?",
      "answers": {
        "a": "atleast one",
        "b": "atmost one",
        "c": "exactly one"
      },
      "explanations": {
        "a": "Explanation 1",
        "b": "Explanation 2",
        "c": "Explanation 2"
      },
      "correctAnswer": "a",
      "difficulty": "beginner"
    },
    {
      "question": "Can an NFA be converted to a DFA?",
      "answers": {
        "a": "yes",
        "b": "no",
        "c": "yes for only simple DFAs"
      },
      "explanations": {
        "a": "Explanation 1",
        "b": "Explanation 2",
        "c": "Explanation 2"
      },
      "correctAnswer": "a",
      "difficulty": "beginner"
    },
    {
      "question": "Can an NFA be constructed such that the final symbol in input has occured before?",
      "answers": {
        "a": "yes",
        "b": "no"
      },
      "explanations": {
        "a": "Explanation 1",
        "b": "Explanation 2"
      },
      "correctAnswer": "a",
      "difficulty": "beginner"
    },
    {
      "question": "Can an NFA be constructed such that the final symbol in input has never occured?",
      "answers": {
        "a": "yes",
        "b": "no"
      },
      "explanations": {
        "a": "Explanation 1",
        "b": "Explanation 2"
      },
      "correctAnswer": "a",
      "difficulty": "beginner"
    }
  ]
}
